dashkit/__init__.py
dashkit/buttons.py
dashkit/callout.py
dashkit/card.py
dashkit/charts.py
dashkit/header.py
dashkit/layout.py
dashkit/logo.py
dashkit/markdown_report.py
dashkit/navigation.py
dashkit/sidebar.py
dashkit/table.py
dashkit/theme_manager.py
dashkit/assets/style.css
dash_dashkit-1.5.0.dist-info/METADATA
dash_dashkit-1.5.0.dist-info/WHEEL
dash_dashkit-1.5.0.dist-info/licenses/LICENSE
dash_dashkit-1.5.0.dist-info/RECORD
