Metadata-Version: 2.4
Name: dash-dashkit
Version: 1.5.0
Summary: Modern dashboard components for Dash applications
Project-URL: Homepage, https://pypi.org/project/dash-dashkit/
Project-URL: Source, https://github.com/iamgp/dash_dashkit
Project-URL: Issues, https://github.com/iamgp/dash_dashkit/issues
Author: Dashkit Team
License: MIT
License-File: LICENSE
Keywords: charts,components,dash,dashboard,handsontable,plotly,tailwind,ui
Classifier: Framework :: Dash
Classifier: Intended Audience :: Developers
Classifier: License :: OSI Approved :: MIT License
Classifier: Programming Language :: Python :: 3
Classifier: Programming Language :: Python :: 3 :: Only
Classifier: Programming Language :: Python :: 3.10
Classifier: Programming Language :: Python :: 3.11
Classifier: Programming Language :: Python :: 3.12
Classifier: Topic :: Software Development :: User Interfaces
Requires-Python: >=3.10
Requires-Dist: dash-bootstrap-components>=1.5.0
Requires-Dist: dash-iconify>=0.1.2
Requires-Dist: dash-mantine-components>=2.1.0
Requires-Dist: dash>=2.17.0
Requires-Dist: dashkit-table>=1.1.2
Requires-Dist: plotly>=5.17.0
Requires-Dist: pyyaml>=6.0.2
Provides-Extra: all
Requires-Dist: dashkit-kiboui>=1.0.1; extra == 'all'
Requires-Dist: dashkit-shadcn>=1.0.1; extra == 'all'
Provides-Extra: charts
Requires-Dist: dashkit-shadcn>=1.0.1; extra == 'charts'
Provides-Extra: dev
Requires-Dist: basedpyright>=1.10.0; extra == 'dev'
Requires-Dist: ruff>=0.1.0; extra == 'dev'
Provides-Extra: kiboui
Requires-Dist: dashkit-kiboui>=1.0.1; extra == 'kiboui'
